<?xml version="1.0" encoding="utf-8"?>
<diff>
	<add sel="//components/component/connections">
		<connection name="con_shieldgen_xl_02" tags="extralarge shield">
				<offset>
						<position x="0.055400000000000005" y="-111.0295" z="105.47500000000001"/>
						<quaternion qw="1.7320510330969933e-07" qx="-0.7071067811865369" qy="-0.0" qz="0.7071067811865369"/>
				</offset>
		</connection>

		<connection group="group_back_bottom" name="con_shieldgen_m_016" tags="medium shield hittable">
				<offset>
						<position x="0.2291" y="179.4082" z="-1136.1376"/>
						<quaternion qw="-0.5000000443375536" qx="0.49999998522081457" qy="-0.49999998522081457" qz="0.49999998522081457"/>
				</offset>
		</connection>
		<connection group="group_back_bottom" name="con_shieldgen_m_017" tags="medium shield hittable">
				<offset>
						<position x="155.3039" y="-89.79169999999999" z="-1135.9190999999998"/>
						<quaternion qw="-0.6830126379815838" qx="0.6830126801437515" qy="-0.18301286173420625" qz="0.18301286173420625"/>
				</offset>
		</connection>
		<connection group="group_back_bottom" name="con_shieldgen_m_018" tags="medium shield hittable">
				<offset>
						<position x="-155.33950000000002" y="-89.6117" z="-1135.9203"/>
						<quaternion qw="-0.6830126379815838" qx="0.6830126801437515" qy="0.18301286173420625" qz="-0.18301286173420625"/>
				</offset>
		</connection>
	</add>
</diff>
